README.md
setup.py
fbroadrunner/__init__.py
fbroadrunner/exceptions.py
fbroadrunner/functions.py
fbroadrunner.egg-info/PKG-INFO
fbroadrunner.egg-info/SOURCES.txt
fbroadrunner.egg-info/dependency_links.txt
fbroadrunner.egg-info/not-zip-safe
fbroadrunner.egg-info/requires.txt
fbroadrunner.egg-info/top_level.txt